MANIFEST.in
README.rst
pyproject.toml
requirements.txt
setup.cfg
setup.py
t_dentrix_service/__init__.py
t_dentrix_service/ascend_service.py
t_dentrix_service/dentrix_service.py
t_dentrix_service/exceptions.py
t_dentrix_service.egg-info/PKG-INFO
t_dentrix_service.egg-info/SOURCES.txt
t_dentrix_service.egg-info/dependency_links.txt
t_dentrix_service.egg-info/not-zip-safe
t_dentrix_service.egg-info/requires.txt
t_dentrix_service.egg-info/top_level.txt
t_dentrix_service/consts/__init__.py
t_dentrix_service/consts/locators.py
t_dentrix_service/consts/urls/__init__.py
t_dentrix_service/consts/urls/ascend_urls.py
t_dentrix_service/consts/urls/dentrix_urls.py
t_dentrix_service/models/__init__.py
t_dentrix_service/models/activity_status.py
t_dentrix_service/models/attachment_types.py
t_dentrix_service/models/eligibility_flag.py
t_dentrix_service/models/ownership_types.py
t_dentrix_service/models/dtos/__init__.py
t_dentrix_service/models/dtos/aged_receivables.py
t_dentrix_service/models/dtos/billing_statement.py
t_dentrix_service/models/dtos/charge.py
t_dentrix_service/models/dtos/document.py
t_dentrix_service/models/dtos/ledger_balance.py
t_dentrix_service/models/dtos/location.py
t_dentrix_service/models/dtos/patient.py
t_dentrix_service/models/dtos/patient_ledger_transaction.py
t_dentrix_service/models/dtos/patient_procedure.py
t_dentrix_service/models/dtos/payer.py
t_dentrix_service/models/dtos/procedure_code.py
t_dentrix_service/models/dtos/provider.py
t_dentrix_service/models/dtos/schedules.py
t_dentrix_service/models/dtos/transaction.py
t_dentrix_service/models/dtos/xray.py
t_dentrix_service/operations/__init__.py
t_dentrix_service/operations/ascend_requests.py
t_dentrix_service/operations/decorators.py
t_dentrix_service/operations/dentrix_login.py
t_dentrix_service/operations/dentrix_requests.py
t_dentrix_service/utils/__init__.py
t_dentrix_service/utils/converters.py
t_dentrix_service/utils/date.py
t_dentrix_service/utils/encrypt.py
t_dentrix_service/utils/logger.py
t_dentrix_service/utils/timer.py
tests/test_ascend_service.py
tests/test_dentrix_service.py
tests/test_models.py