Metadata-Version: 2.4
Name: t_dentrix_service
Version: 1.2.1
Summary: Service for handling Dentrix processes.
Home-page: https://www.thoughtful.ai/
Author: Thoughtful
Author-email: support@thoughtful.ai
Keywords: t_dentrix_service
Classifier: Intended Audience :: Developers
Classifier: Natural Language :: English
Classifier: Programming Language :: Python :: 3
Classifier: Programming Language :: Python :: 3.11
Requires-Python: >=3.11.5
Requires-Dist: rpaframework>=28.1.0
Requires-Dist: retry~=0.9.2
Requires-Dist: fake-useragent>=1.4.0
Requires-Dist: pytest>=7.2.0
Requires-Dist: t_object~=0.1.7
Requires-Dist: pycryptodome>=3.21.0
Requires-Dist: numpy>=2.2.4
Dynamic: author
Dynamic: author-email
Dynamic: classifier
Dynamic: description
Dynamic: description-content-type
Dynamic: home-page
Dynamic: keywords
Dynamic: requires-dist
Dynamic: requires-python
Dynamic: summary
